tellurium/VERSION.txt
tellurium/__init__.py
tellurium/tellurium.py
tellurium/temiriam.py
tellurium/testcases.py
tellurium/analysis/__init__.py
tellurium/analysis/annotations.py
tellurium/analysis/bifurcation.py
tellurium/analysis/parameterestimation.py
tellurium/analysis/parameterscan.py
tellurium/analysis/sensitivityanalysis.py
tellurium/analysis/simulator.py
tellurium/analysis/stochasticmodel.py
tellurium/analysis/test.py
tellurium/notebooks/__init__.py
tellurium/notebooks/notebooktools.py
tellurium/notebooks/ontologysearch.py
tellurium/notebooks/parameterslider.py
tellurium/notebooks/speciessearch.py
tellurium/plotting/__init__.py
tellurium/plotting/api.py
tellurium/plotting/engine.py
tellurium/plotting/engine_mpl.py
tellurium/plotting/engine_null.py
tellurium/plotting/engine_plotly.py
tellurium/plotting/factory.py
tellurium/roadrunner/__init__.py
tellurium/roadrunner/extended_roadrunner.py
tellurium/sedml/__init__.py
tellurium/sedml/data.py
tellurium/sedml/mathml.py
tellurium/sedml/tesedml.py
tellurium/sedml/utils.py
tellurium/sedml/xpath.py
tellurium/sedml/templates/macros_helpers.template
tellurium/sedml/templates/tesedml_template.template
tellurium/teconverters/__init__.py
tellurium/teconverters/antimony_regex.py
tellurium/teconverters/antimony_sbo.py
tellurium/teconverters/convert_antimony.py
tellurium/teconverters/convert_omex.py
tellurium/teconverters/convert_phrasedml.py
tellurium/teconverters/inline_omex.py
tellurium/teio/__init__.py
tellurium/teio/latex.py
tellurium/utils/__init__.py
tellurium/utils/matrix.py
tellurium/utils/misc.py
tellurium/utils/omex.py
tellurium/utils/package.py
tellurium/utils/uncertainty.py
tellurium/visualization/__init__.py
tellurium/visualization/sbmldiagram.py
tellurium-2.2.11.2.dist-info/licenses/LICENSE.txt
tellurium-2.2.11.2.dist-info/licenses/NOTICE.txt
tellurium-2.2.11.2.dist-info/METADATA
tellurium-2.2.11.2.dist-info/WHEEL
tellurium-2.2.11.2.dist-info/top_level.txt
tellurium-2.2.11.2.dist-info/RECORD
