Metadata-Version: 2.4
Name: tellurium
Version: 2.2.11.2
Summary: Tellurium: An biological modeling environment for Python
Home-page: http://tellurium.analogmachine.org/
Author: J. Kyle Medley, Kiri Choi, Matthias König, Lucian Smith, Herbert M. Sauro
License-File: LICENSE.txt
License-File: NOTICE.txt
Requires-Dist: numpy>=1.23
Requires-Dist: scipy>=1.5.1
Requires-Dist: matplotlib>=2.0.2
Requires-Dist: pandas>=2.0
Requires-Dist: libroadrunner>=2.8
Requires-Dist: antimony>=3.1.0
Requires-Dist: python-libsbml>=5.20
Requires-Dist: python-libnuml>=1.0.0
Requires-Dist: python-libsedml>=2.0.17
Requires-Dist: python-libcombine>=0.2.2
Requires-Dist: appdirs>=1.4.3
Requires-Dist: jinja2>=3.0.0
Requires-Dist: plotly>=2.0.12
Requires-Dist: requests
Requires-Dist: jupyter-client>=5.1.0
Requires-Dist: jupyter-core>=4.3.0
Requires-Dist: ipython
Requires-Dist: ipykernel>=4.6.1
Requires-Dist: pytest
Requires-Dist: sbml2matlab>=0.9.1; python_version < "3.10" and platform_machine != "arm64"
Requires-Dist: phrasedml>=1.0.9; platform_machine != "arm64"
Requires-Dist: rrplugins>=2.1; platform_system == "Windows"
Dynamic: author
Dynamic: description
Dynamic: description-content-type
Dynamic: home-page
Dynamic: license-file
Dynamic: provides-extra
Dynamic: requires-dist
Dynamic: summary
